pyecodevices_rt2/__init__.py
pyecodevices_rt2/abstractsensor.py
pyecodevices_rt2/abstractswitch.py
pyecodevices_rt2/cli.py
pyecodevices_rt2/const.py
pyecodevices_rt2/counter.py
pyecodevices_rt2/digitalinput.py
pyecodevices_rt2/ecodevices_rt2.py
pyecodevices_rt2/enocean.py
pyecodevices_rt2/exceptions.py
pyecodevices_rt2/post.py
pyecodevices_rt2/relay.py
pyecodevices_rt2/supplierindex.py
pyecodevices_rt2/toroid.py
pyecodevices_rt2/virtualoutput.py
pyecodevices_rt2/x4fp.py
pyecodevices_rt2/xthl.py
pyecodevices_rt2-1.3.4.dist-info/AUTHORS.rst
pyecodevices_rt2-1.3.4.dist-info/LICENSE
pyecodevices_rt2-1.3.4.dist-info/METADATA
pyecodevices_rt2-1.3.4.dist-info/WHEEL
pyecodevices_rt2-1.3.4.dist-info/entry_points.txt
pyecodevices_rt2-1.3.4.dist-info/top_level.txt
pyecodevices_rt2-1.3.4.dist-info/RECORD
