Metadata-Version: 2.1
Name: pyecodevices-rt2
Version: 1.3.4
Summary: Get information from GCE Ecodevices RT2.
Home-page: https://github.com/pcourbin/pyecodevices_rt2
Author: Pierre COURBIN
Author-email: pierre.courbin@gmail.com
License: MIT license
Keywords: pyecodevices_rt2
Platform: UNKNOWN
Classifier: Development Status :: 4 - Beta
Classifier: Intended Audience :: Developers
Classifier: License :: OSI Approved :: MIT License
Classifier: Natural Language :: English
Classifier: Programming Language :: Python :: 3
Classifier: Programming Language :: Python :: 3.5
Classifier: Programming Language :: Python :: 3.6
Classifier: Programming Language :: Python :: 3.7
Classifier: Programming Language :: Python :: 3.8
Classifier: Programming Language :: Python :: 3.9
Requires-Python: >=3.5
License-File: LICENSE
License-File: AUTHORS.rst
Requires-Dist: Click (>=7.0)
